ruobr_student/__init__.py
ruobr_student/cookie.py
ruobr_student/excel.py
ruobr_student/exceptions.py
ruobr_student/extra.py
ruobr_student/marks.py
ruobr_student/ruobr.py
ruobr_student/schedule.py
ruobr_student/types.py
ruobr_student-1.1.1.dist-info/METADATA
ruobr_student-1.1.1.dist-info/WHEEL
ruobr_student-1.1.1.dist-info/RECORD
