Metadata-Version: 2.1
Name: ruobr-student
Version: 1.1.1
Summary: Доступ к данным cabinet.ruobr.ru для студентов
Author: QuoNaro
Author-email: QuoNaro@mail.ru
Requires-Python: >=3.10
Classifier: Programming Language :: Python :: 3
Classifier: Programming Language :: Python :: 3.10
Classifier: Programming Language :: Python :: 3.11
Requires-Dist: aiohttp (==3.8.5)
Requires-Dist: asyncio (==3.4.3)
Requires-Dist: beautifulsoup4 (==4.12.2)
Requires-Dist: lxml (==4.9.3)
Requires-Dist: requests (==2.31.0)
